{"172.21.1.224": {"name": "\u30de\u30a6\u30f3\u30c8\u30b5\u30d61\u53f7\u6a5f", "product": [3817, 0, 0, 0, 0, 0, 0], "alarm": [0, 9, 1]}, "172.21.1.229": {"name": "\u30de\u30a6\u30f3\u30c8\u30b5\u30d63\u53f7\u6a5f", "product": [1854, 0, 0, 0, 0, 0, 0], "alarm": [2, 0, 0]}, "172.21.1.225": {"name": "\u30de\u30a6\u30f3\u30c8\u30b5\u30d65\u53f7\u6a5f", "product": [4575, 0, 0, 0, 0, 0, 0], "alarm": [2, 0, 0]}, "172.21.1.223": {"name": "\u30de\u30a6\u30f3\u30c8\u30b5\u30d62\u53f7\u6a5f", "product": [1601, 0, 0, 0, 0, 0, 0], "alarm": [0, 1, 1]}, "172.21.1.215": {"name": "\u30de\u30a6\u30f3\u30c8\u30b5\u30d64\u53f7\u6a5f", "product": [2049, 0, 0, 0, 0, 0, 0], "alarm": [0, 0, 0]}}